karmakraft/__init__.py
karmakraft/_main.py
karmakraft-2.0.1.dist-info/LICENSE
karmakraft-2.0.1.dist-info/METADATA
karmakraft-2.0.1.dist-info/WHEEL
karmakraft-2.0.1.dist-info/RECORD
