Metadata-Version: 2.1
Name: karmakraft
Version: 2.0.1
Summary: API component for Knew Karma
Home-page: https://github.com/knewkarma-io/karmakraft
License: GPL-3.0+
Author: Richard Mwewa
Author-email: rly0nheart@duck.com
Requires-Python: >=3.10,<4.0
Classifier: License :: OSI Approved :: GNU General Public License v3 or later (GPLv3+)
Classifier: Programming Language :: Python :: 3
Classifier: Programming Language :: Python :: 3.10
Classifier: Programming Language :: Python :: 3.11
Classifier: Programming Language :: Python :: 3.12
Classifier: Programming Language :: Python :: 3.13
Requires-Dist: aiohttp (>=3.10.10,<4.0.0)
Requires-Dist: karmakaze (>=1.5.0,<2.0.0)
